Metadata-Version: 2.1
Name: QuartzAI
Version: 0.1
Summary: An AI Coding Friend Package
Home-page: UNKNOWN
Author: pwntrackdev
Author-email: pwntrackdev@gmail.com
License: UNKNOWN
Platform: UNKNOWN
